{
  "description": "项目配置文件",
  "packOptions": {
    "ignore": []
  },
  "setting": {
    "urlCheck": false,
    "es6": true,
    "enhance": true,
    "postcss": true,
    "preloadBackgroundData": false,
    "minified": true,
    "newFeature": true,
    "coverView": true,
    "nodeModules": true,
    "autoAudits": false,
    "showShadowRootInWxmlPanel": false,
    "scopeDataCheck": false,
    "uglifyFileName": false,
    "checkInvalidKey": true,
    "checkSiteMap": true,
    "uploadWithSourceMap": true,
    "compileHotReLoad": true,
    "lazyloadPlaceholderEnable": false,
    "useMultiFrameRuntime": true,
    "useApiHook": true,
    "useApiHostProcess": true,
    "babelSetting": {
      "ignore": [],
      "disablePlugins": [],
      "outputPath": ""
    },
    "enableEngineNative": false,
    "useIsolateContext": true,
    "userConfirmedBundleSwitch": false,
    "packNpmManually": false,
    "packNpmRelationList": [],
    "minifyWXSS": true,
    "disableUseStrict": false,
    "showES6CompileOption": false,
    "useCompilerPlugins": false,
    "minifyWXML": true
  },
  "compileType": "miniprogram",
  "libVersion": "2.16.1",
  "appid": "wx97f75401b664ce99",
  "projectname": "%E6%B3%89%E5%A4%A9%E4%B8%8B",
  "debugOptions": {
    "hidedInDevtools": []
  },
  "isGameTourist": false,
  "simulatorType": "wechat",
  "simulatorPluginLibVersion": {},
  "condition": {
    "plugin": {
      "list": []
    },
    "game": {
      "list": []
    },
    "gamePlugin": {
      "list": []
    },
    "miniprogram": {
      "list": [
        {
          "id": 0,
          "name": "pages/troupe/index",
          "pathName": "pages/troupe/index/index",
          "query": "",
          "scene": null
        },
        {
          "id": -1,
          "name": "pages/invite/index",
          "pathName": "pages/invite/index",
          "query": "",
          "scene": null
        },
        {
          "name": "pages/live/index",
          "pathName": "pages/live/index",
          "scene": null
        }
      ]
    }
  }
}